pip_robot/__init__.py
pip_robot/__main__.py
pip_robot/loglevel.py
pip_robot/pip_robot.py
pip_robot/run_cmd.py
pip_robot-0.1.0a4.dist-info/entry_points.txt
pip_robot-0.1.0a4.dist-info/LICENSE
pip_robot-0.1.0a4.dist-info/WHEEL
pip_robot-0.1.0a4.dist-info/METADATA
pip_robot-0.1.0a4.dist-info/RECORD
